dictionary/__init__.py
dictionary/dictionary.py
HW1_CI_CD-2.0.0.dist-info/METADATA
HW1_CI_CD-2.0.0.dist-info/WHEEL
HW1_CI_CD-2.0.0.dist-info/top_level.txt
HW1_CI_CD-2.0.0.dist-info/RECORD
