Metadata-Version: 2.1
Name: HW1-CI-CD
Version: 2.0.0
Summary: UNKNOWN
Author: Abdumbo99
License: UNKNOWN
Platform: UNKNOWN
Requires-Python: >=3.8
Requires-Dist: requests (>=2.23.0)
